{
  "bot": "fafnir",
  "competition_id": "arb-20260323-0110",
  "league": "arb",
  "duration_hours": 168,
  "started_at": "2026-03-23T01:10:01.198736+00:00",
  "pair_a": "SOL/USD",
  "pair_b": "BTC/USD",
  "spread_name": "SOL/BTC",
  "starting_capital": 1000.0,
  "fee_rate": 0.001,
  "equity": 999.65,
  "peak_equity": 1000.0,
  "positions": [
    {
      "pair": "SOL/USD vs BTC/USD",
      "direction": "short",
      "pair_a": "SOL/USD",
      "pair_b": "BTC/USD",
      "entry_ratio": 0.00129672,
      "entry_z": 2.0579,
      "entry_price_a": 92.337,
      "entry_price_b": 71208.0,
      "size_usd": 350.0,
      "opened_at": "2026-03-25T09:30:02.082697+00:00"
    }
  ],
  "stats": {
    "total_trades": 0,
    "wins": 0,
    "losses": 0,
    "win_rate": 0.0,
    "total_pnl_usd": 0.0,
    "total_pnl_pct": 0.0,
    "total_fees": 0.35,
    "max_drawdown_pct": 0.0,
    "current_equity": 999.65
  }
}